setup.py
delcoder_distributions.egg-info/PKG-INFO
delcoder_distributions.egg-info/SOURCES.txt
delcoder_distributions.egg-info/dependency_links.txt
delcoder_distributions.egg-info/not-zip-safe
delcoder_distributions.egg-info/top_level.txt
distributions/Binomialdistribution.py
distributions/Gaussiandistribution.py
distributions/Generaldistribution.py
distributions/__init__.py