Metadata-Version: 1.0
Name: delcoder-distributions
Version: 0.24
Summary: Gaussian distributions
Home-page: UNKNOWN
Author: UNKNOWN
Author-email: UNKNOWN
License: UNKNOWN
Platform: UNKNOWN
